bit_vault_warden_client/__init__.py
bit_vault_warden_client/bcrypt.py
bit_vault_warden_client/client.py
bit_vault_warden_client/errors.py
bit_vault_warden_client/helpers.py
bit_vault_warden_client/models.py
bit_vault_warden_client-1.0.0.dist-info/METADATA
bit_vault_warden_client-1.0.0.dist-info/WHEEL
bit_vault_warden_client-1.0.0.dist-info/RECORD
