Metadata-Version: 2.4
Name: bit-vault-warden-client
Version: 1.0.0
Summary: A Python client to fetch data from Bitwarden and Vaultwarden
Project-URL: Homepage, https://github.com/Q24/python-bit-vault-warden-client
Project-URL: Repository, https://github.com/Q24/python-bit-vault-warden-client
Author-email: Olegs Capligins <ocapligins@ilionx.com>, Arjen Buising <abuising@ilionx.com>, Tonny Nguyen <tnguyen@ilionx.com>, Martijn Suijlen <msuijlen@ilionx.com>
License-Expression: MIT
Classifier: Development Status :: 4 - Beta
Classifier: Intended Audience :: Developers
Classifier: License :: OSI Approved :: MIT License
Classifier: Programming Language :: Python :: 3 :: Only
Requires-Python: >=3.8
Requires-Dist: cryptography
Requires-Dist: requests
Requires-Dist: requests[socks]
